byo/__init__.py
byo/bench.py
byo/coroutines.py
byo-0.1.0.dist-info/METADATA
byo-0.1.0.dist-info/WHEEL
byo-0.1.0.dist-info/licenses/LICENSE
byo-0.1.0.dist-info/RECORD
