Metadata-Version: 2.4
Name: byo
Version: 0.1.0
Summary: Simple benchmarking decorator
Project-URL: Homepage, https://github.com/kntng/byo
Project-URL: Repository, https://github.com/kntng/byo.git
Project-URL: Issues, https://github.com/kntng/byo/issues
Author-email: Kenneth Tang <kntng@kntng.dev>
License: MIT
License-File: LICENSE
Requires-Python: >=3.7
Requires-Dist: tabulate
